influx_requests.py
influx_requests-1.0.1.dev5.dist-info/DESCRIPTION.rst
influx_requests-1.0.1.dev5.dist-info/METADATA
influx_requests-1.0.1.dev5.dist-info/RECORD
influx_requests-1.0.1.dev5.dist-info/WHEEL
influx_requests-1.0.1.dev5.dist-info/metadata.json
influx_requests-1.0.1.dev5.dist-info/top_level.txt
